ghcloneall.py
ghcloneall-1.12.0.dist-info/LICENCE
ghcloneall-1.12.0.dist-info/METADATA
ghcloneall-1.12.0.dist-info/WHEEL
ghcloneall-1.12.0.dist-info/entry_points.txt
ghcloneall-1.12.0.dist-info/top_level.txt
ghcloneall-1.12.0.dist-info/RECORD
