Metadata-Version: 2.1
Name: ghcloneall
Version: 1.12.0
Summary: Clone/update all user/organization GitHub repositories
Home-page: https://github.com/mgedmin/ghcloneall
Author: Marius Gedminas
Author-email: marius@gedmin.as
License: MIT
Keywords: github git clone automation
Classifier: Development Status :: 4 - Beta
Classifier: Environment :: Console
Classifier: Intended Audience :: Developers
Classifier: License :: OSI Approved :: MIT License
Classifier: Operating System :: OS Independent
Classifier: Programming Language :: Python :: 3.7
Classifier: Programming Language :: Python :: 3.8
Classifier: Programming Language :: Python :: 3.9
Classifier: Programming Language :: Python :: 3.10
Classifier: Programming Language :: Python :: 3.11
Classifier: Programming Language :: Python :: 3.12
Classifier: Programming Language :: Python :: 3.13
Classifier: Programming Language :: Python :: Implementation :: CPython
Classifier: Programming Language :: Python :: Implementation :: PyPy
License-File: LICENCE
Requires-Dist: requests
Requires-Dist: requests-cache
